{
    "chapter": 0,
    "level": 0,
    "background": "04-17.png",
    "motto": "The only disability in life is a bad attitude.",
    "author": "Figure Skater, Scott Hamilton",
    "answer": "only|life|bad|attitude",
    "theme": "04-17",
    "targetWord": 4,
    "column": 8,
    "row": 15,
    "time": 40,
    "targetLetter": 0,
    "targetType": 0,
    "map": [
        "H",
        "B",
        "I",
        "G",
        "I",
        "E",
        "R",
        "C",
        "U",
        "Z",
        "J",
        "F",
        "W",
        "L",
        "A",
        "Z",
        "A",
        "Z",
        "E",
        "O",
        "T",
        "G",
        "R",
        "K",
        "Q",
        "S",
        "W",
        "B",
        "J",
        "D",
        "Y",
        "T",
        "H",
        "D",
        "Z",
        "C",
        "Y",
        "N",
        "C",
        "T",
        "X",
        "K",
        "R",
        "B",
        "L",
        "R",
        "F",
        "O",
        "J",
        "C",
        "I",
        "E",
        "H",
        "K",
        "G",
        "R",
        "Q",
        "Y",
        "S",
        "X",
        "S",
        "V",
        "E",
        "A",
        "F",
        "V",
        "X",
        "U",
        "X",
        "O",
        "B",
        "D",
        "B",
        "A",
        "D",
        "L",
        "Z",
        "K",
        "Y",
        "P",
        "Q",
        "C",
        "T",
        "L",
        "I",
        "F",
        "E",
        "F",
        "K",
        "O",
        "O",
        "L",
        "R",
        "A",
        "O",
        "T",
        "H",
        "D",
        "I",
        "O",
        "N",
        "L",
        "Y",
        "A",
        "W",
        "P",
        "B",
        "B",
        "R",
        "L",
        "O",
        "G",
        "A",
        "T",
        "T",
        "I",
        "T",
        "U",
        "D",
        "E"
    ],
    "extraanswer": "BIG|LOG|ITU|DION|LIFE|ATTITUDE|BAD|ATT|ONLY|TIT|KOOL|ION|RAO"
}