{
    "chapter": 0,
    "level": 0,
    "background": "20200528.png",
    "motto": "I would like to listen in and listen out into you, into the world, into the woods.",
    "author": "Poet, Rainer Maria Rilke",
    "answer": "world|wood|like|listen",
    "theme": "2020-05-28T00:00:00",
    "targetWord": 4,
    "column": 7,
    "row": 14,
    "time": 40,
    "targetLetter": 0,
    "targetType": 0,
    "map": [
        "S",
        "M",
        "P",
        "P",
        "J",
        "A",
        "U",
        "C",
        "K",
        "X",
        "P",
        "F",
        "O",
        "O",
        "V",
        "L",
        "I",
        "S",
        "T",
        "E",
        "N",
        "Q",
        "V",
        "N",
        "F",
        "M",
        "G",
        "K",
        "M",
        "I",
        "V",
        "S",
        "C",
        "H",
        "L",
        "O",
        "R",
        "K",
        "Z",
        "G",
        "B",
        "L",
        "Z",
        "C",
        "J",
        "U",
        "H",
        "H",
        "W",
        "P",
        "V",
        "Q",
        "L",
        "I",
        "K",
        "E",
        "Y",
        "C",
        "W",
        "J",
        "H",
        "N",
        "X",
        "A",
        "X",
        "S",
        "B",
        "N",
        "S",
        "X",
        "H",
        "W",
        "O",
        "O",
        "D",
        "X",
        "Z",
        "Z",
        "X",
        "N",
        "K",
        "H",
        "A",
        "J",
        "H",
        "X",
        "P",
        "C",
        "D",
        "G",
        "Y",
        "W",
        "O",
        "R",
        "L",
        "D",
        "T",
        "I"
    ],
    "extraanswer": "LIKE|SMP|STE|WOO|TEN|LIS|LIST|FOO|WOOD|IST|WORLD|LISTEN|SCH"
}