{
    "chapter": 0,
    "level": 0,
    "background": "08-10.png",
    "motto": "Life is something that happens when you can't get to sleep.",
    "author": "Author, Fran Lebowitz",
    "answer": "sleep|something|happen",
    "theme": "08-10",
    "targetWord": 3,
    "column": 9,
    "row": 16,
    "time": 40,
    "targetLetter": 0,
    "targetType": 0,
    "map": [
        "U",
        "A",
        "C",
        "A",
        "X",
        "V",
        "Z",
        "A",
        "B",
        "O",
        "K",
        "F",
        "J",
        "B",
        "G",
        "D",
        "T",
        "V",
        "Y",
        "U",
        "N",
        "Y",
        "U",
        "P",
        "F",
        "K",
        "Z",
        "X",
        "S",
        "L",
        "E",
        "E",
        "P",
        "M",
        "W",
        "Z",
        "E",
        "C",
        "J",
        "M",
        "S",
        "T",
        "A",
        "M",
        "E",
        "C",
        "U",
        "E",
        "T",
        "M",
        "S",
        "J",
        "M",
        "Z",
        "U",
        "N",
        "X",
        "G",
        "J",
        "G",
        "V",
        "L",
        "N",
        "M",
        "R",
        "G",
        "H",
        "A",
        "P",
        "P",
        "E",
        "N",
        "K",
        "M",
        "F",
        "C",
        "Z",
        "M",
        "R",
        "P",
        "Q",
        "A",
        "L",
        "O",
        "S",
        "N",
        "P",
        "L",
        "I",
        "T",
        "C",
        "B",
        "R",
        "T",
        "N",
        "W",
        "N",
        "I",
        "G",
        "Y",
        "O",
        "K",
        "C",
        "J",
        "E",
        "L",
        "X",
        "K",
        "U",
        "E",
        "U",
        "F",
        "X",
        "S",
        "X",
        "M",
        "Z",
        "H",
        "G",
        "Y",
        "G",
        "Z",
        "Q",
        "U",
        "I",
        "L",
        "P",
        "P",
        "F",
        "H",
        "E",
        "B",
        "X",
        "S",
        "T",
        "S",
        "O",
        "M",
        "E",
        "T",
        "H",
        "I",
        "N",
        "G"
    ],
    "extraanswer": "HAP|CUE|QUI|METH|ACA|SOME|YUP|LIT|SOMETHING|APP|ING|TAM|MET|HAPPEN|THIN|THING|LEE|SLEEP|PEN|SOM"
}