{
    "chapter": 0,
    "level": 0,
    "background": "4.png",
    "motto": "Don't cry because it's over. Smile because it happened.",
    "author": "Author, Dr. Seuss",
    "answer": "happen|smile|over|because|cry",
    "theme": "famous quote",
    "targetWord": 5,
    "column": 9,
    "row": 16,
    "time": 40,
    "targetLetter": 0,
    "targetType": 0,
    "map": [
        "Q",
        "E",
        "U",
        "I",
        "P",
        "N",
        "U",
        "V",
        "R",
        "F",
        "X",
        "H",
        "A",
        "P",
        "P",
        "E",
        "N",
        "Q",
        "R",
        "X",
        "O",
        "E",
        "F",
        "G",
        "L",
        "I",
        "J",
        "E",
        "N",
        "O",
        "V",
        "E",
        "R",
        "N",
        "Z",
        "M",
        "T",
        "N",
        "K",
        "S",
        "I",
        "H",
        "E",
        "M",
        "I",
        "H",
        "S",
        "Q",
        "N",
        "K",
        "T",
        "M",
        "Z",
        "O",
        "Q",
        "B",
        "E",
        "C",
        "A",
        "U",
        "S",
        "E",
        "Q",
        "W",
        "S",
        "X",
        "L",
        "O",
        "I",
        "K",
        "I",
        "C",
        "R",
        "J",
        "J",
        "T",
        "Z",
        "P",
        "E",
        "F",
        "X",
        "G",
        "Y",
        "L",
        "Z",
        "Z",
        "Y",
        "P",
        "O",
        "D",
        "J",
        "Q",
        "C",
        "R",
        "Y",
        "E",
        "T",
        "E",
        "N",
        "Y",
        "A",
        "D",
        "M",
        "C",
        "H",
        "T",
        "M",
        "M",
        "H",
        "J",
        "O",
        "G",
        "E",
        "C",
        "O",
        "W",
        "J",
        "I",
        "R",
        "G",
        "S",
        "M",
        "I",
        "L",
        "E",
        "J",
        "M",
        "V",
        "L",
        "Q",
        "E",
        "Q",
        "G",
        "I",
        "G",
        "W",
        "J",
        "W",
        "R",
        "I",
        "P",
        "X",
        "N",
        "V"
    ],
    "extraanswer": "APP|NOV|VER|SEQ|YET|CRY|EMI|ILE|ECO|PEN|HTM|MILE|DMC|GIG|COW|RIP|RYE|SMILE|CAUSE|GSM|MIL|ADM|HAPPEN|HEM|USE|AUS|POD|TEN|OVER|BECAUSE"
}