{
    "chapter": 0,
    "level": 0,
    "background": "45.png",
    "motto": "Some unseen fingers, like an idle breeze, are playing upon my heart the music of the ripples.",
    "author": "Poet, Rabindranath Tagore",
    "answer": "idle|heart|music|breeze",
    "theme": "2019-10-22",
    "targetWord": 4,
    "column": 9,
    "row": 16,
    "time": 40,
    "targetLetter": 0,
    "targetType": 0,
    "map": [
        "W",
        "C",
        "M",
        "R",
        "K",
        "Z",
        "M",
        "W",
        "Q",
        "T",
        "R",
        "C",
        "Z",
        "Z",
        "T",
        "J",
        "Z",
        "M",
        "H",
        "D",
        "O",
        "K",
        "Q",
        "E",
        "E",
        "X",
        "D",
        "Y",
        "E",
        "B",
        "V",
        "V",
        "P",
        "B",
        "J",
        "B",
        "G",
        "S",
        "B",
        "R",
        "E",
        "E",
        "Z",
        "E",
        "L",
        "H",
        "O",
        "C",
        "H",
        "T",
        "P",
        "R",
        "M",
        "W",
        "K",
        "V",
        "M",
        "U",
        "S",
        "I",
        "C",
        "J",
        "E",
        "H",
        "M",
        "S",
        "P",
        "G",
        "M",
        "O",
        "W",
        "T",
        "R",
        "O",
        "P",
        "T",
        "F",
        "H",
        "S",
        "Y",
        "U",
        "F",
        "F",
        "R",
        "X",
        "I",
        "D",
        "L",
        "E",
        "G",
        "U",
        "B",
        "U",
        "X",
        "R",
        "R",
        "X",
        "O",
        "P",
        "H",
        "O",
        "X",
        "Q",
        "Y",
        "N",
        "X",
        "S",
        "Z",
        "F",
        "M",
        "Q",
        "G",
        "L",
        "S",
        "G",
        "X",
        "V",
        "N",
        "J",
        "B",
        "R",
        "M",
        "A",
        "K",
        "W",
        "N",
        "F",
        "I",
        "K",
        "H",
        "E",
        "A",
        "R",
        "T",
        "J",
        "F",
        "S",
        "E",
        "B",
        "I",
        "J",
        "G",
        "E",
        "S"
    ],
    "extraanswer": "LEG|KVM|ART|HOC|HEAR|MUS|BREEZE|EAR|OCH|SIC|MUSIC|HMS|IDLE|HEART|OPT"
}