{
    "chapter": 0,
    "level": 0,
    "background": "12.png",
    "motto": "There are no shortcuts to any place worth going.",
    "author": "Musician, Beverly Sills",
    "answer": "worth|place|shortcut",
    "theme": "2019-11-20",
    "targetWord": 3,
    "column": 9,
    "row": 16,
    "time": 40,
    "targetLetter": 0,
    "targetType": 0,
    "map": [
        "B",
        "N",
        "C",
        "N",
        "I",
        "G",
        "E",
        "Q",
        "C",
        "K",
        "Z",
        "W",
        "M",
        "V",
        "Y",
        "U",
        "W",
        "O",
        "Q",
        "S",
        "R",
        "H",
        "P",
        "L",
        "A",
        "C",
        "E",
        "G",
        "Y",
        "N",
        "N",
        "H",
        "Q",
        "G",
        "J",
        "T",
        "V",
        "V",
        "S",
        "Q",
        "C",
        "Z",
        "M",
        "W",
        "E",
        "P",
        "L",
        "J",
        "Q",
        "U",
        "O",
        "O",
        "V",
        "D",
        "S",
        "H",
        "O",
        "R",
        "T",
        "C",
        "U",
        "T",
        "X",
        "K",
        "Q",
        "W",
        "O",
        "R",
        "T",
        "H",
        "O",
        "C",
        "U",
        "Y",
        "O",
        "H",
        "T",
        "S",
        "N",
        "H",
        "F",
        "L",
        "H",
        "R",
        "J",
        "V",
        "J",
        "M",
        "B",
        "J",
        "H",
        "H",
        "O",
        "O",
        "W",
        "T",
        "Y",
        "T",
        "V",
        "Z",
        "H",
        "Q",
        "M",
        "S",
        "P",
        "F",
        "N",
        "X",
        "L",
        "Z",
        "N",
        "J",
        "V",
        "Y",
        "N",
        "T",
        "X",
        "K",
        "Y",
        "I",
        "A",
        "E",
        "K",
        "O",
        "B",
        "H",
        "E",
        "P",
        "V",
        "D",
        "S",
        "U",
        "Z",
        "R",
        "N",
        "A",
        "R",
        "H",
        "B",
        "B",
        "V",
        "H",
        "A",
        "W"
    ],
    "extraanswer": "QUO|HOC|PLACE|ACE|ORTHO|WMV|SHORTCUT|TSN|WORTH|SHORT|CUT|LAC|SPF|THO|LACE"
}