{
    "chapter": 0,
    "level": 0,
    "background": "51.png",
    "motto": "There is a light somewhere. It may not be much light but it beats the darkness.",
    "author": "Poet, Charles Bukowski",
    "answer": "beats|darkness|light|somewhere",
    "theme": "11-4",
    "targetWord": 4,
    "column": 9,
    "row": 16,
    "time": 40,
    "targetLetter": 0,
    "targetType": 0,
    "map": [
        "P",
        "D",
        "G",
        "E",
        "P",
        "Y",
        "A",
        "E",
        "V",
        "P",
        "J",
        "P",
        "P",
        "I",
        "A",
        "A",
        "L",
        "Q",
        "C",
        "C",
        "H",
        "T",
        "A",
        "A",
        "H",
        "J",
        "L",
        "S",
        "O",
        "M",
        "E",
        "W",
        "H",
        "E",
        "R",
        "E",
        "G",
        "V",
        "X",
        "J",
        "E",
        "E",
        "V",
        "H",
        "S",
        "C",
        "V",
        "V",
        "V",
        "F",
        "G",
        "W",
        "V",
        "G",
        "H",
        "Y",
        "V",
        "X",
        "C",
        "B",
        "M",
        "Z",
        "H",
        "R",
        "Z",
        "C",
        "L",
        "X",
        "A",
        "A",
        "D",
        "M",
        "V",
        "Q",
        "T",
        "D",
        "L",
        "I",
        "G",
        "H",
        "T",
        "R",
        "H",
        "Z",
        "X",
        "A",
        "P",
        "L",
        "H",
        "V",
        "E",
        "U",
        "R",
        "W",
        "Z",
        "B",
        "V",
        "T",
        "S",
        "I",
        "S",
        "P",
        "Q",
        "R",
        "L",
        "J",
        "V",
        "G",
        "I",
        "Z",
        "B",
        "E",
        "A",
        "T",
        "S",
        "F",
        "F",
        "N",
        "A",
        "R",
        "H",
        "F",
        "S",
        "Y",
        "A",
        "C",
        "N",
        "K",
        "G",
        "O",
        "S",
        "R",
        "L",
        "H",
        "P",
        "D",
        "A",
        "R",
        "K",
        "N",
        "E",
        "S",
        "S",
        "J"
    ],
    "extraanswer": "EAT|ARK|DARKNESS|EUR|SOM|EATS|DAR|LIGHT|SOME|ISP|HER|WHERE|BEA|VHS|URW|ADM|BEAT|HERE|SOMEWHERE|ATS|BEATS|SRL|DARK|ESS|NES|NESS"
}